parasol_lca/__init__.py
parasol_lca/_activities.py
parasol_lca/_parameters.py
parasol_lca-1.0.2.dist-info/licenses/COPYING
parasol_lca-1.0.2.dist-info/METADATA
parasol_lca-1.0.2.dist-info/WHEEL
parasol_lca-1.0.2.dist-info/top_level.txt
parasol_lca-1.0.2.dist-info/RECORD
