Metadata-Version: 2.4
Name: parasol-lca
Version: 1.0.2
Summary: Implement parasol LCA database
Author-email: Romain BESSEAU <romain.besseau@ec.europa.eu>, Alejandra CUE GONZALEZ <alejandra.cue_gonzalez@minesparis.psl.eu>, Benoît GSCHWIND <benoit.gschwind@minesparis.psl.eu>
Maintainer-email: Alejandra CUE GONZALEZ <alejandra.cue_gonzalez@minesparis.psl.eu>
Project-URL: Homepage, https://github.com/oie-mines-paristech/parasol-lca
Project-URL: Documentation, https://github.com/oie-mines-paristech/parasol-lca
Project-URL: Repository, https://github.com/oie-mines-paristech/parasol-lca
Project-URL: Issues, https://github.com/oie-mines-paristech/parasol-lca/issues
Keywords: lca,ecoinvent,photovoltaic
Classifier: Programming Language :: Python :: 3.10
Classifier: Programming Language :: Python :: 3.11
Classifier: Programming Language :: Python :: 3.12
Classifier: Programming Language :: Python :: 3.13
Requires-Python: >=3.10
License-File: COPYING
Requires-Dist: lca_algebraic==1.2
Dynamic: license-file
